dmPython.cp37-win_amd64.pyd
dmPythonClient-2.5.5.dist-info/METADATA
dmPythonClient-2.5.5.dist-info/WHEEL
dmPythonClient-2.5.5.dist-info/top_level.txt
dmPythonClient-2.5.5.dist-info/RECORD
