Metadata-Version: 2.1
Name: dmPythonClient
Version: 2.5.5
Summary: Python interface to Dameng
Home-page: UNKNOWN
Author: UNKNOWN
Author-email: UNKNOWN
License: Python Software Foundation License
Keywords: Dameng
Platform: UNKNOWN
Classifier: Development Status :: 6 - Mature
Classifier: Intended Audience :: Developers
Classifier: Natural Language :: English
Classifier: Operating System :: OS Independent
Classifier: Programming Language :: C
Classifier: Programming Language :: Python
Classifier: Programming Language :: Python :: 2
Classifier: Programming Language :: Python :: 3
Classifier: Topic :: Database
